{"job_id":"job_2026-04-14T223523.0501598Z_demo-recon-success","job_type":"recon_artifact_mainline","contract_key":"black-box/recon/sd15-ddim","status":"completed","workspace_name":"demo-recon-success","created_at":"2026-04-14T22:35:23.0501598Z","updated_at":"2026-04-14T22:35:30.6388885Z","payload":{"job_type":"recon_artifact_mainline","contract_key":"black-box/recon/sd15-ddim","workspace_name":"demo-recon-success","runtime_profile":"local","job_inputs":{"artifact_dir":"<DIFFAUDIT_ROOT>/Research/experiments/recon-runtime-mainline-ddim-public-100-step30/score-artifacts","method":"threshold"}},"command":["python","<DIFFAUDIT_ROOT>/Runtime-Server/runners/recon-runner/run.py","run-recon-artifact-mainline","--artifact-dir","<DIFFAUDIT_ROOT>/Research/experiments/recon-runtime-mainline-ddim-public-100-step30/score-artifacts","--workspace","<DIFFAUDIT_ROOT>/Research/experiments/demo-recon-success","--repo-root","<DIFFAUDIT_ROOT>/Research/external/Reconstruction-based-Attack","--method","threshold"],"summary_path":"<DIFFAUDIT_ROOT>/Research/experiments/demo-recon-success/summary.json","metrics":{"asr":0.51,"auc":0.849,"tpr_at_1pct_fpr":1},"error":null,"stdout_tail":null,"stderr_tail":null}